LICENSE
MANIFEST.in
README.md
example.py
setup.py
financialCrawler/__init__.py
financialCrawler.egg-info/PKG-INFO
financialCrawler.egg-info/SOURCES.txt
financialCrawler.egg-info/dependency_links.txt
financialCrawler.egg-info/requires.txt
financialCrawler.egg-info/top_level.txt
financialCrawler/clients/__init__.py
financialCrawler/clients/base.py
financialCrawler/clients/bigpara.py
financialCrawler/clients/google.py
financialCrawler/clients/marketwatch.py
financialCrawler/clients/twsj.py
financialCrawler/clients/uzmanpara.py