Metadata-Version: 1.0
Name: financialCrawler
Version: 0.1.0.7
Summary: stock price crawler
Home-page: https://github.com/muatik/financial-crawler
Author: Mustafa Atik
Author-email: muatik@gmail.com
License: MIT
Platform: any
